j2p/__init__.py
j2p/main.py
j2p-0.0.2.dist-info/METADATA
j2p-0.0.2.dist-info/WHEEL
j2p-0.0.2.dist-info/entry_points.txt
j2p-0.0.2.dist-info/top_level.txt
j2p-0.0.2.dist-info/RECORD
