Metadata-Version: 2.1
Name: j2p
Version: 0.0.2
Summary: Un outil qui permet de convertif une classe Java en classe Python !
Home-page: https://macademia.fr
Author: Abdel Macademia
Author-email: abdel@macademia.fr
License: UNKNOWN
Keywords: java,python
Platform: any
Classifier: Development Status :: 3 - Alpha
Classifier: Intended Audience :: Developers
Classifier: License :: OSI Approved :: MIT License
Classifier: Operating System :: OS Independent
Classifier: Programming Language :: Python
Classifier: Programming Language :: Python :: 2.7
Classifier: Programming Language :: Python :: 3.3
Classifier: Programming Language :: Python :: 3.4
Classifier: Programming Language :: Python :: 3.5
Classifier: Programming Language :: Python :: 3.6
Classifier: Programming Language :: Python :: 3.7
Classifier: Topic :: Software Development :: Libraries :: Python Modules
Requires-Python: !=3.0.*,!=3.1.*,!=3.2.*,>=2.7
Requires-Dist: black
